acumbamail/__init__.py
acumbamail/aclient.py
acumbamail/client.py
acumbamail/exceptions.py
acumbamail/models.py
acumbamail/utils.py
acumbamail-0.1.4.dist-info/LICENSE
acumbamail-0.1.4.dist-info/METADATA
acumbamail-0.1.4.dist-info/WHEEL
acumbamail-0.1.4.dist-info/RECORD
