Metadata-Version: 2.3
Name: acumbamail
Version: 0.1.4
Summary: Acumamail SDK client for Python
License: MIT
Author: Daniel Garcia (cr0hn)
Requires-Python: >=3.11
Classifier: License :: OSI Approved :: MIT License
Classifier: Programming Language :: Python :: 3
Classifier: Programming Language :: Python :: 3.11
Classifier: Programming Language :: Python :: 3.12
Classifier: Programming Language :: Python :: 3.13
Requires-Dist: httpx (>=0.28.1,<0.29.0)
